{
  "session_num": 74,
  "last_saved": 1784417436.821912,
  "history": [
    {
      "tick": 44,
      "session": 74,
      "ts": 1784417364.3416555,
      "objects": [
        {
          "label": "hotbar",
          "conf": 0.91
        },
        {
          "label": "xp_bar",
          "conf": 0.88
        },
        {
          "label": "health_bar",
          "conf": 0.87
        },
        {
          "label": "hunger_bar",
          "conf": 0.82
        },
        {
          "label": "armor_bar",
          "conf": 0.45
        },
        {
          "label": "leaves",
          "conf": 0.75
        },
        {
          "label": "zombie",
          "conf": 0.75
        },
        {
          "label": "spider",
          "conf": 0.75
        }
      ],
      "action": "s"
    },
    {
      "tick": 45,
      "session": 74,
      "ts": 1784417365.8573797,
      "objects": [
        {
          "label": "hotbar",
          "conf": 0.91
        },
        {
          "label": "health_bar",
          "conf": 0.86
        },
        {
          "label": "hunger_bar",
          "conf": 0.85
        },
        {
          "label": "xp_bar",
          "conf": 0.84
        },
        {
          "label": "armor_bar",
          "conf": 0.67
        },
        {
          "label": "hunger_bar",
          "conf": 0.27
        },
        {
          "label": "xp_bar",
          "conf": 0.12
        },
        {
          "label": "leaves",
          "conf": 0.75
        },
        {
          "label": "zombie",
          "conf": 0.75
        },
        {
          "label": "spider",
          "conf": 0.75
        }
      ],
      "action": "s"
    },
    {
      "tick": 46,
      "session": 74,
      "ts": 1784417366.8738668,
      "objects": [
        {
          "label": "hotbar",
          "conf": 0.91
        },
        {
          "label": "health_bar",
          "conf": 0.86
        },
        {
          "label": "xp_bar",
          "conf": 0.84
        },
        {
          "label": "hunger_bar",
          "conf": 0.84
        },
        {
          "label": "armor_bar",
          "conf": 0.67
        },
        {
          "label": "hunger_bar",
          "conf": 0.13
        },
        {
          "label": "xp_bar",
          "conf": 0.13
        },
        {
          "label": "leaves",
          "conf": 0.75
        },
        {
          "label": "zombie",
          "conf": 0.75
        },
        {
          "label": "spider",
          "conf": 0.75
        }
      ],
      "action": "s"
    },
    {
      "tick": 47,
      "session": 74,
      "ts": 1784417368.387911,
      "objects": [
        {
          "label": "hotbar",
          "conf": 0.91
        },
        {
          "label": "health_bar",
          "conf": 0.86
        },
        {
          "label": "hunger_bar",
          "conf": 0.83
        },
        {
          "label": "xp_bar",
          "conf": 0.83
        },
        {
          "label": "armor_bar",
          "conf": 0.69
        },
        {
          "label": "leaves",
          "conf": 0.75
        },
        {
          "label": "zombie",
          "conf": 0.75
        },
        {
          "label": "spider",
          "conf": 0.75
        }
      ],
      "action": "s"
    },
    {
      "tick": 48,
      "session": 74,
      "ts": 1784417369.9026856,
      "objects": [
        {
          "label": "hotbar",
          "conf": 0.91
        },
        {
          "label": "hunger_bar",
          "conf": 0.85
        },
        {
          "label": "health_bar",
          "conf": 0.85
        },
        {
          "label": "xp_bar",
          "conf": 0.85
        },
        {
          "label": "armor_bar",
          "conf": 0.6
        },
        {
          "label": "xp_bar",
          "conf": 0.11
        },
        {
          "label": "leaves",
          "conf": 0.75
        },
        {
          "label": "zombie",
          "conf": 0.75
        },
        {
          "label": "spider",
          "conf": 0.75
        }
      ],
      "action": "s"
    },
    {
      "tick": 49,
      "session": 74,
      "ts": 1784417388.5836895,
      "objects": [
        {
          "label": "hotbar",
          "conf": 0.91
        },
        {
          "label": "health_bar",
          "conf": 0.85
        },
        {
          "label": "hunger_bar",
          "conf": 0.84
        },
        {
          "label": "xp_bar",
          "conf": 0.84
        },
        {
          "label": "armor_bar",
          "conf": 0.71
        },
        {
          "label": "xp_bar",
          "conf": 0.15
        },
        {
          "label": "hunger_bar",
          "conf": 0.13
        },
        {
          "label": "leaves",
          "conf": 0.75
        },
        {
          "label": "zombie",
          "conf": 0.75
        },
        {
          "label": "spider",
          "conf": 0.75
        }
      ],
      "action": "s"
    },
    {
      "tick": 50,
      "session": 74,
      "ts": 1784417389.5935721,
      "objects": [
        {
          "label": "hotbar",
          "conf": 0.91
        },
        {
          "label": "health_bar",
          "conf": 0.85
        },
        {
          "label": "xp_bar",
          "conf": 0.85
        },
        {
          "label": "hunger_bar",
          "conf": 0.85
        },
        {
          "label": "armor_bar",
          "conf": 0.61
        },
        {
          "label": "xp_bar",
          "conf": 0.13
        },
        {
          "label": "leaves",
          "conf": 0.75
        },
        {
          "label": "zombie",
          "conf": 0.75
        },
        {
          "label": "spider",
          "conf": 0.75
        }
      ],
      "action": "s"
    },
    {
      "tick": 51,
      "session": 74,
      "ts": 1784417401.0065088,
      "objects": [
        {
          "label": "hotbar",
          "conf": 0.91
        },
        {
          "label": "health_bar",
          "conf": 0.87
        },
        {
          "label": "hunger_bar",
          "conf": 0.84
        },
        {
          "label": "xp_bar",
          "conf": 0.83
        },
        {
          "label": "armor_bar",
          "conf": 0.72
        },
        {
          "label": "xp_bar",
          "conf": 0.12
        },
        {
          "label": "leaves",
          "conf": 0.75
        },
        {
          "label": "zombie",
          "conf": 0.75
        },
        {
          "label": "spider",
          "conf": 0.75
        }
      ],
      "action": "s"
    },
    {
      "tick": 52,
      "session": 74,
      "ts": 1784417402.5184987,
      "objects": [
        {
          "label": "hotbar",
          "conf": 0.91
        },
        {
          "label": "xp_bar",
          "conf": 0.86
        },
        {
          "label": "hunger_bar",
          "conf": 0.86
        },
        {
          "label": "health_bar",
          "conf": 0.85
        },
        {
          "label": "armor_bar",
          "conf": 0.61
        },
        {
          "label": "leaves",
          "conf": 0.75
        },
        {
          "label": "zombie",
          "conf": 0.75
        },
        {
          "label": "spider",
          "conf": 0.75
        }
      ],
      "action": "s"
    },
    {
      "tick": 53,
      "session": 74,
      "ts": 1784417404.0308304,
      "objects": [
        {
          "label": "hotbar",
          "conf": 0.91
        },
        {
          "label": "hunger_bar",
          "conf": 0.85
        },
        {
          "label": "health_bar",
          "conf": 0.85
        },
        {
          "label": "xp_bar",
          "conf": 0.84
        },
        {
          "label": "armor_bar",
          "conf": 0.56
        },
        {
          "label": "xp_bar",
          "conf": 0.12
        },
        {
          "label": "leaves",
          "conf": 0.75
        },
        {
          "label": "zombie",
          "conf": 0.75
        },
        {
          "label": "spider",
          "conf": 0.75
        }
      ],
      "action": "s"
    },
    {
      "tick": 54,
      "session": 74,
      "ts": 1784417405.5420415,
      "objects": [
        {
          "label": "hotbar",
          "conf": 0.91
        },
        {
          "label": "xp_bar",
          "conf": 0.85
        },
        {
          "label": "hunger_bar",
          "conf": 0.85
        },
        {
          "label": "health_bar",
          "conf": 0.84
        },
        {
          "label": "armor_bar",
          "conf": 0.67
        },
        {
          "label": "hunger_bar",
          "conf": 0.17
        },
        {
          "label": "xp_bar",
          "conf": 0.12
        },
        {
          "label": "leaves",
          "conf": 0.75
        },
        {
          "label": "zombie",
          "conf": 0.75
        },
        {
          "label": "spider",
          "conf": 0.75
        }
      ],
      "action": "s"
    },
    {
      "tick": 55,
      "session": 74,
      "ts": 1784417407.0525591,
      "objects": [
        {
          "label": "hotbar",
          "conf": 0.91
        },
        {
          "label": "hunger_bar",
          "conf": 0.87
        },
        {
          "label": "health_bar",
          "conf": 0.85
        },
        {
          "label": "xp_bar",
          "conf": 0.85
        },
        {
          "label": "armor_bar",
          "conf": 0.71
        },
        {
          "label": "hunger_bar",
          "conf": 0.19
        },
        {
          "label": "xp_bar",
          "conf": 0.13
        },
        {
          "label": "leaves",
          "conf": 0.75
        },
        {
          "label": "zombie",
          "conf": 0.75
        },
        {
          "label": "spider",
          "conf": 0.75
        }
      ],
      "action": "s"
    },
    {
      "tick": 56,
      "session": 74,
      "ts": 1784417408.56683,
      "objects": [
        {
          "label": "hotbar",
          "conf": 0.91
        },
        {
          "label": "xp_bar",
          "conf": 0.86
        },
        {
          "label": "hunger_bar",
          "conf": 0.86
        },
        {
          "label": "health_bar",
          "conf": 0.84
        },
        {
          "label": "armor_bar",
          "conf": 0.61
        },
        {
          "label": "hunger_bar",
          "conf": 0.19
        },
        {
          "label": "xp_bar",
          "conf": 0.14
        },
        {
          "label": "leaves",
          "conf": 0.75
        },
        {
          "label": "zombie",
          "conf": 0.75
        },
        {
          "label": "spider",
          "conf": 0.75
        }
      ],
      "action": "s"
    },
    {
      "tick": 57,
      "session": 74,
      "ts": 1784417426.6547642,
      "objects": [
        {
          "label": "hotbar",
          "conf": 0.91
        },
        {
          "label": "xp_bar",
          "conf": 0.86
        },
        {
          "label": "hunger_bar",
          "conf": 0.84
        },
        {
          "label": "health_bar",
          "conf": 0.83
        },
        {
          "label": "armor_bar",
          "conf": 0.47
        },
        {
          "label": "xp_bar",
          "conf": 0.14
        },
        {
          "label": "hunger_bar",
          "conf": 0.1
        },
        {
          "label": "leaves",
          "conf": 0.75
        },
        {
          "label": "zombie",
          "conf": 0.75
        },
        {
          "label": "spider",
          "conf": 0.75
        }
      ],
      "action": "s"
    },
    {
      "tick": 58,
      "session": 74,
      "ts": 1784417428.1654336,
      "objects": [
        {
          "label": "hotbar",
          "conf": 0.91
        },
        {
          "label": "hunger_bar",
          "conf": 0.87
        },
        {
          "label": "health_bar",
          "conf": 0.85
        },
        {
          "label": "xp_bar",
          "conf": 0.82
        },
        {
          "label": "armor_bar",
          "conf": 0.64
        },
        {
          "label": "hunger_bar",
          "conf": 0.19
        },
        {
          "label": "xp_bar",
          "conf": 0.14
        },
        {
          "label": "leaves",
          "conf": 0.75
        },
        {
          "label": "zombie",
          "conf": 0.75
        },
        {
          "label": "spider",
          "conf": 0.75
        }
      ],
      "action": "s"
    },
    {
      "tick": 59,
      "session": 74,
      "ts": 1784417429.6776266,
      "objects": [
        {
          "label": "hotbar",
          "conf": 0.91
        },
        {
          "label": "hunger_bar",
          "conf": 0.86
        },
        {
          "label": "xp_bar",
          "conf": 0.83
        },
        {
          "label": "health_bar",
          "conf": 0.83
        },
        {
          "label": "armor_bar",
          "conf": 0.56
        },
        {
          "label": "hunger_bar",
          "conf": 0.3
        },
        {
          "label": "xp_bar",
          "conf": 0.13
        },
        {
          "label": "log",
          "conf": 0.408
        },
        {
          "label": "leaves",
          "conf": 0.75
        },
        {
          "label": "zombie",
          "conf": 0.75
        },
        {
          "label": "spider",
          "conf": 0.75
        }
      ],
      "action": "s"
    },
    {
      "tick": 60,
      "session": 74,
      "ts": 1784417431.1881874,
      "objects": [
        {
          "label": "hotbar",
          "conf": 0.91
        },
        {
          "label": "hunger_bar",
          "conf": 0.86
        },
        {
          "label": "health_bar",
          "conf": 0.85
        },
        {
          "label": "xp_bar",
          "conf": 0.85
        },
        {
          "label": "armor_bar",
          "conf": 0.73
        },
        {
          "label": "hunger_bar",
          "conf": 0.21
        },
        {
          "label": "xp_bar",
          "conf": 0.12
        },
        {
          "label": "log",
          "conf": 0.75
        },
        {
          "label": "leaves",
          "conf": 0.75
        },
        {
          "label": "zombie",
          "conf": 0.75
        },
        {
          "label": "spider",
          "conf": 0.75
        }
      ],
      "action": "s"
    },
    {
      "tick": 61,
      "session": 74,
      "ts": 1784417432.7049947,
      "objects": [
        {
          "label": "hotbar",
          "conf": 0.91
        },
        {
          "label": "hunger_bar",
          "conf": 0.86
        },
        {
          "label": "xp_bar",
          "conf": 0.85
        },
        {
          "label": "health_bar",
          "conf": 0.83
        },
        {
          "label": "armor_bar",
          "conf": 0.65
        },
        {
          "label": "hunger_bar",
          "conf": 0.19
        },
        {
          "label": "xp_bar",
          "conf": 0.11
        },
        {
          "label": "log",
          "conf": 0.75
        },
        {
          "label": "leaves",
          "conf": 0.75
        },
        {
          "label": "zombie",
          "conf": 0.75
        },
        {
          "label": "spider",
          "conf": 0.75
        }
      ],
      "action": "s"
    },
    {
      "tick": 62,
      "session": 74,
      "ts": 1784417434.2157106,
      "objects": [
        {
          "label": "hotbar",
          "conf": 0.91
        },
        {
          "label": "xp_bar",
          "conf": 0.86
        },
        {
          "label": "hunger_bar",
          "conf": 0.86
        },
        {
          "label": "health_bar",
          "conf": 0.85
        },
        {
          "label": "armor_bar",
          "conf": 0.72
        },
        {
          "label": "hunger_bar",
          "conf": 0.16
        },
        {
          "label": "log",
          "conf": 0.75
        },
        {
          "label": "leaves",
          "conf": 0.75
        },
        {
          "label": "zombie",
          "conf": 0.75
        },
        {
          "label": "spider",
          "conf": 0.75
        }
      ],
      "action": "s"
    },
    {
      "tick": 63,
      "session": 74,
      "ts": 1784417435.7261395,
      "objects": [
        {
          "label": "hotbar",
          "conf": 0.91
        },
        {
          "label": "xp_bar",
          "conf": 0.84
        },
        {
          "label": "health_bar",
          "conf": 0.82
        },
        {
          "label": "hunger_bar",
          "conf": 0.82
        },
        {
          "label": "armor_bar",
          "conf": 0.74
        },
        {
          "label": "log",
          "conf": 0.75
        },
        {
          "label": "leaves",
          "conf": 0.75
        },
        {
          "label": "zombie",
          "conf": 0.75
        },
        {
          "label": "spider",
          "conf": 0.75
        }
      ],
      "action": "s"
    }
  ],
  "chunks": {
    "-1_1": {
      "ores_seen": {
        "emerald_ore": {
          "pos": [
            -14.0,
            64,
            23.0
          ],
          "tick": 349
        },
        "diamond_ore": {
          "pos": [
            -6.0,
            64,
            23.0
          ],
          "tick": 86
        },
        "coal_ore": {
          "pos": [
            -14.0,
            64,
            23.0
          ],
          "tick": 231
        }
      },
      "threats_seen": [],
      "resources": {},
      "visited_at": 350
    },
    "0_-1": {
      "ores_seen": {
        "emerald_ore": {
          "pos": [
            1.0,
            64,
            -13.0
          ],
          "tick": 61
        },
        "lapis_ore": {
          "pos": [
            11.0,
            64,
            -13.0
          ],
          "tick": 126
        }
      },
      "threats_seen": [],
      "resources": {},
      "visited_at": 50
    },
    "0_1": {
      "ores_seen": {},
      "threats_seen": [],
      "resources": {},
      "visited_at": 50
    },
    "-2_2": {
      "ores_seen": {},
      "threats_seen": [],
      "resources": {},
      "visited_at": 50
    },
    "-2_1": {
      "ores_seen": {
        "emerald_ore": {
          "pos": [
            -26.0,
            64,
            21.0
          ],
          "tick": 137
        }
      },
      "threats_seen": [],
      "resources": {},
      "visited_at": 50
    },
    "-1_-2": {
      "ores_seen": {},
      "threats_seen": [],
      "resources": {},
      "visited_at": 50
    }
  },
  "base_location": null,
  "spawn_point": [
    -6.0,
    64,
    23.0
  ]
}